{
  "status": 200,
  "item": {
    "id": 1001,
    "title": "Fresh Movie One",
    "type": "movie",
    "subtype": null,
    "year": 2025,
    "cast": "Actor A, Actor B",
    "director": "Director X",
    "voice": "Voice Studio",
    "duration": { "average": 120, "total": 120 },
    "langs": 2,
    "ac3": 1,
    "quality": 1080,
    "poor_quality": false,
    "plot": "A thrilling adventure movie about heroes saving the world.",
    "imdb": 12345,
    "imdb_rating": 7.5,
    "imdb_votes": 10000,
    "kinopoisk": 54321,
    "kinopoisk_rating": 7.8,
    "kinopoisk_votes": 5000,
    "rating": 8,
    "rating_votes": 200,
    "rating_percentage": 85,
    "views": 5000,
    "comments": 50,
    "finished": true,
    "advert": false,
    "in_watchlist": false,
    "subscribed": false,
    "created_at": 1700000000,
    "updated_at": 1700000000,
    "posters": {
      "small": "https://via.placeholder.com/100x150/1a2a4a/ffffff?text=F1",
      "medium": "https://via.placeholder.com/250x375/1a2a4a/ffffff?text=F1",
      "big": "https://via.placeholder.com/500x750/1a2a4a/ffffff?text=F1",
      "wide": "https://via.placeholder.com/1280x720/1a2a4a/ffffff?text=F1"
    },
    "trailer": { "id": 0, "url": "" },
    "genres": [{ "id": 1, "title": "Action", "type": "movie" }],
    "countries": [{ "id": 1, "title": "USA" }],
    "bookmarks": [],
    "videos": [
      {
        "id": 5001,
        "title": "Fresh Movie One",
        "number": 1,
        "snumber": 0,
        "thumbnail": "https://via.placeholder.com/320x180/1a2a4a/ffffff?text=thumb",
        "duration": 7200,
        "watched": 0,
        "watching": { "status": 0, "time": 0 },
        "tracks": 2,
        "ac3": 1,
        "audios": [
          { "id": 1, "index": 0, "codec": "aac", "channels": 6, "lang": "eng" },
          { "id": 2, "index": 1, "codec": "aac", "channels": 2, "lang": "rus" }
        ],
        "subtitles": [
          { "lang": "eng", "shift": 0, "embed": false, "forced": false, "file": "sub_en.srt", "url": "https://example.com/sub_en.srt" },
          { "lang": "rus", "shift": 0, "embed": false, "forced": false, "file": "sub_ru.srt", "url": "https://example.com/sub_ru.srt" }
        ]
      }
    ]
  }
}
